django_embed_template/__init__.py
django_embed_template/templatetags/__init__.py
django_embed_template/templatetags/embed.py
django_embed_template-0.2.0.dist-info/DESCRIPTION.rst
django_embed_template-0.2.0.dist-info/METADATA
django_embed_template-0.2.0.dist-info/RECORD
django_embed_template-0.2.0.dist-info/WHEEL
django_embed_template-0.2.0.dist-info/metadata.json
django_embed_template-0.2.0.dist-info/top_level.txt
