Metadata-Version: 2.0
Name: django-embed-template
Version: 0.2.0
Summary: Override blocks in included templates
Home-page: https://github.com/joostrijneveld/django-embed-template
Author: Joost Rijneveld
Author-email: joost@joostrijneveld.nl
License: CC0
Keywords: django templates embedding
Platform: UNKNOWN
Classifier: Development Status :: 4 - Beta
Classifier: Intended Audience :: Developers
Classifier: Topic :: Software Development :: User Interfaces
Classifier: License :: CC0 1.0 Universal (CC0 1.0) Public Domain Dedication
Classifier: Programming Language :: Python :: 2
Classifier: Programming Language :: Python :: 2.7
Classifier: Programming Language :: Python :: 3
Classifier: Programming Language :: Python :: 3.2
Classifier: Programming Language :: Python :: 3.3
Classifier: Programming Language :: Python :: 3.4
Classifier: Programming Language :: Python :: 3.5
Requires-Dist: django (>=1.8)
